odoo/addons/currency_rate_update_nbp/LICENSE
odoo/addons/currency_rate_update_nbp/README.rst
odoo/addons/currency_rate_update_nbp/__init__.py
odoo/addons/currency_rate_update_nbp/__manifest__.py
odoo/addons/currency_rate_update_nbp/models/__init__.py
odoo/addons/currency_rate_update_nbp/models/res_currency_rate_provider_nbp.py
odoo/addons/currency_rate_update_nbp/readme/CONFIGURE.rst
odoo/addons/currency_rate_update_nbp/readme/CONTRIBUTORS.rst
odoo/addons/currency_rate_update_nbp/readme/DESCRIPTION.rst
odoo/addons/currency_rate_update_nbp/readme/INSTALL.rst
odoo/addons/currency_rate_update_nbp/readme/ROADMAP.rst
odoo/addons/currency_rate_update_nbp/static/description/icon.png
odoo/addons/currency_rate_update_nbp/static/description/index.html
odoo/addons/currency_rate_update_nbp/tests/__init__.py
odoo/addons/currency_rate_update_nbp/tests/response_data.py
odoo/addons/currency_rate_update_nbp/tests/test_res_currency_rate_provider.py
odoo/addons/currency_rate_update_nbp/wizards/res_currency_rate_update_wizard.xml
odoo14_addon_currency_rate_update_nbp-14.0.1.0.1.dev3.dist-info/METADATA
odoo14_addon_currency_rate_update_nbp-14.0.1.0.1.dev3.dist-info/WHEEL
odoo14_addon_currency_rate_update_nbp-14.0.1.0.1.dev3.dist-info/top_level.txt
odoo14_addon_currency_rate_update_nbp-14.0.1.0.1.dev3.dist-info/RECORD
